chatgpt_anon/__init__.py
chatgpt_anon/helpers.py
chatgpt_anon/main.py
chatgpt_anon-0.1.0.dist-info/WHEEL
chatgpt_anon-0.1.0.dist-info/entry_points.txt
chatgpt_anon-0.1.0.dist-info/METADATA
chatgpt_anon-0.1.0.dist-info/RECORD
