Metadata-Version: 2.3
Name: chatgpt-anon
Version: 0.1.0
Summary: Intreract with ChatGPT anonymously
Author: smartwa
Author-email: smartwa <smartwacaleb@gmail.com>
Requires-Dist: httpx>=0.28.1
Requires-Dist: mkdocs-material>=9.6.17
Requires-Python: >=3.13
